{
  "parent": "minecraft:recipes/root",
  "criteria": {
    "has_enderite_shield": {
      "conditions": {
        "items": [
          {
            "items": [
              "xores:enderite_shield"
            ]
          }
        ]
      },
      "trigger": "minecraft:inventory_changed"
    },
    "has_night_ingot": {
      "conditions": {
        "items": [
          {
            "items": [
              "xores:night_ingot"
            ]
          }
        ]
      },
      "trigger": "minecraft:inventory_changed"
    },
    "has_night_shield": {
      "conditions": {
        "items": [
          {
            "items": [
              "xores:night_shield"
            ]
          }
        ]
      },
      "trigger": "minecraft:inventory_changed"
    },
    "has_the_recipe": {
      "conditions": {
        "recipe": "xores:night_shield_smithing"
      },
      "trigger": "minecraft:recipe_unlocked"
    }
  },
  "requirements": [
    [
      "has_enderite_shield",
      "has_night_ingot",
      "has_night_shield",
      "has_the_recipe"
    ]
  ],
  "rewards": {
    "recipes": [
      "xores:night_shield_smithing"
    ]
  }
}